MANIFEST.in
README.rst
setup.cfg
setup.py
sneklang.py
test_snek.py
sneklang.egg-info/PKG-INFO
sneklang.egg-info/SOURCES.txt
sneklang.egg-info/dependency_links.txt
sneklang.egg-info/requires.txt
sneklang.egg-info/top_level.txt