Metadata-Version: 2.1
Name: sneklang
Version: 0.4.6
Summary: Experimental minimal subset of Python for safe evaluation
Home-page: https://github.com/readevalprint/sneklang
Author: Timoth Watts
Author-email: tim@readevalprint.com
License: UNKNOWN
Keywords: sandbox,parse,ast
Platform: UNKNOWN
Classifier: Development Status :: 4 - Beta
Classifier: Intended Audience :: Developers
Classifier: License :: OSI Approved :: MIT License
Classifier: Topic :: Software Development :: Libraries :: Python Modules
Classifier: Programming Language :: Python
